fineng_model/__init__.py
fineng_model/sp.py
fineng_model-0.1.dist-info/LICENSE
fineng_model-0.1.dist-info/METADATA
fineng_model-0.1.dist-info/WHEEL
fineng_model-0.1.dist-info/top_level.txt
fineng_model-0.1.dist-info/RECORD
