Metadata-Version: 2.1
Name: fineng-model
Version: 0.1
Summary: financial model
Home-page: UNKNOWN
Author: haoming wang
Author-email: wanghaoming17@163.com
License: UNKNOWN
Platform: UNKNOWN
Classifier: Programming Language :: Python :: 3
Classifier: License :: OSI Approved :: GNU General Public License (GPL)
Requires-Python: >=3
License-File: LICENSE
Requires-Dist: numpy
